authful_mcp_proxy/__init__.py
authful_mcp_proxy/__main__.py
authful_mcp_proxy/config.py
authful_mcp_proxy/external_oidc.py
authful_mcp_proxy/mcp_proxy.py
authful_mcp_proxy-0.2.2.dist-info/METADATA
authful_mcp_proxy-0.2.2.dist-info/WHEEL
authful_mcp_proxy-0.2.2.dist-info/entry_points.txt
authful_mcp_proxy-0.2.2.dist-info/licenses/LICENSE
authful_mcp_proxy-0.2.2.dist-info/RECORD
