Metadata-Version: 2.4
Name: authful-mcp-proxy
Version: 0.2.2
Summary: A Model Context Protocol (MCP) proxy server that performs OIDC authentication to obtain access tokens for remote MCP servers protected by token validation, and bridges HTTP transport to local stdio for MCP clients like Claude Desktop.
Author-email: Stephan Eberle <stephaneberle9@gmail.com>
License-File: LICENSE
Requires-Python: >=3.10
Requires-Dist: fastmcp>=2.14.0
